Metadata-Version: 2.1
Name: dserial
Version: 0.0.2
Summary: Python data serializer with type checking
Home-page: https://github.com/pjongy/dserial
Author: pjongy
Author-email: whdduq218@gmail.com
License: UNKNOWN
Keywords: serialize,type
Platform: UNKNOWN
Classifier: Programming Language :: Python :: 3
Classifier: Programming Language :: Python :: 3.7
Requires-Python: >=3.7
